haohaninfo_scholar/__init__.py
haohaninfo_scholar/new_receiver/__init__.py
haohaninfo_scholar/new_receiver/new_receiver.pyd
haohaninfo_scholar-0.0.1.dist-info/METADATA
haohaninfo_scholar-0.0.1.dist-info/WHEEL
haohaninfo_scholar-0.0.1.dist-info/top_level.txt
haohaninfo_scholar-0.0.1.dist-info/RECORD
