Metadata-Version: 2.1
Name: haohaninfo-scholar
Version: 0.0.1
Summary: haohaninfo_scholar
Home-page: UNKNOWN
Author: haohaninfo
Author-email: haohanservice@haohaninfo.com
License: UNKNOWN
Platform: UNKNOWN
Classifier: Programming Language :: Python :: 3.6
Classifier: Operating System :: Microsoft :: Windows
Requires-Dist: pika (>=1.0.0)
